apt_preferences/__init__.py
apt_preferences/_constants.py
apt_preferences/_utils.py
apt_preferences/apt_preferences.lark
apt_preferences/data_structures.py
apt_preferences/errors.py
apt_preferences/find_preferences_files.py
apt_preferences/parse_preferences_files.py
apt_preferences/render_preferences_files.py
apt_preferences-0.0.1.dist-info/LICENSE
apt_preferences-0.0.1.dist-info/METADATA
apt_preferences-0.0.1.dist-info/WHEEL
apt_preferences-0.0.1.dist-info/top_level.txt
apt_preferences-0.0.1.dist-info/RECORD
