Metadata-Version: 2.1
Name: apt-preferences
Version: 0.0.1
Summary: Manage apt preferences
Author-email: Jakub Buczyński <jakub@buczynski.net.pl>
Project-URL: Homepage, https://github.com/KubaTaba1uga/python_apt_preferences
Classifier: Operating System :: POSIX :: Linux
Classifier: Programming Language :: Python :: 3
Classifier: License :: OSI Approved :: MIT License
Requires-Python: >=3.9
License-File: LICENSE
Requires-Dist: lark (==1.1.5)
Provides-Extra: dev
Requires-Dist: ruff (==0.0.265) ; extra == 'dev'
Requires-Dist: mypy (==1.3.0) ; extra == 'dev'
Requires-Dist: black (==23.3.0) ; extra == 'dev'
Requires-Dist: isort (==5.12.0) ; extra == 'dev'
Provides-Extra: test
Requires-Dist: pytest (==7.3.1) ; extra == 'test'
